[
    {
        "id": 1,
        "first_name": "Rodney",
        "last_name": "Brabender",
        "email": "rbrabender0@skyrock.com",
        "password": "Un3QQgd4fdZ",
        "address": "14980 Carpenter Hill",
        "gender": "Male",
        "age": 3,
        "country": "Indonesia"
    },
    {
        "id": 2,
        "first_name": "Carlye",
        "last_name": "Hauck",
        "email": "chauck1@wix.com",
        "password": "DtrCS0vhIS",
        "address": "739 Myrtle Street",
        "gender": "Female",
        "age": 11,
        "country": "Russia"
    },
    {
        "id": 3,
        "first_name": "Jenny",
        "last_name": "Francombe",
        "email": "jfrancombe2@issuu.com",
        "password": "aJJvWmuj9",
        "address": "3327 Killdeer Center",
        "gender": "Female",
        "age": 84,
        "country": "Portugal"
    },
    {
        "id": 4,
        "first_name": "Bogart",
        "last_name": "Sharland",
        "email": "bsharland3@yahoo.co.jp",
        "password": "bfd0J0slgcFB",
        "address": "21 Moose Street",
        "gender": "Male",
        "age": 24,
        "country": "Costa Rica"
    },
    {
        "id": 5,
        "first_name": "Harvey",
        "last_name": "Findlow",
        "email": "hfindlow4@google.com.br",
        "password": "2bYNU6Rzm7z",
        "address": "725 Oakridge Road",
        "gender": "Male",
        "age": 42,
        "country": "China"
    },
    {
        "id": 6,
        "first_name": "Grantham",
        "last_name": "Khilkov",
        "email": "gkhilkov5@newsvine.com",
        "password": "rWHIeSLJ",
        "address": "7 Barby Point",
        "gender": "Male",
        "age": 82,
        "country": "Guatemala"
    },
    {
        "id": 7,
        "first_name": "Foss",
        "last_name": "Aspinal",
        "email": "faspinal6@live.com",
        "password": "TlZZIND",
        "address": "78 Surrey Trail",
        "gender": "Male",
        "age": 115,
        "country": "Tunisia"
    },
    {
        "id": 8,
        "first_name": "Gerry",
        "last_name": "Souttar",
        "email": "gsouttar7@multiply.com",
        "password": "5YbNfb",
        "address": "58 Lukken Street",
        "gender": "Male",
        "age": 51,
        "country": "Russia"
    },
    {
        "id": 9,
        "first_name": "Erinna",
        "last_name": "Pyrah",
        "email": "epyrah8@huffingtonpost.com",
        "password": "oUwGPW6nvbPb",
        "address": "950 Carpenter Junction",
        "gender": "Female",
        "age": 98,
        "country": "Thailand"
    },
    {
        "id": 10,
        "first_name": "Anitra",
        "last_name": "Voase",
        "email": "avoase9@soup.io",
        "password": "PoboZvSCsYlw",
        "address": "70 Atwood Park",
        "gender": "Female",
        "age": 42,
        "country": "Poland"
    },
    {
        "id": 11,
        "first_name": "Taffy",
        "last_name": "Papa",
        "email": "tpapaa@techcrunch.com",
        "password": "YfihVlo",
        "address": "3 Maple Center",
        "gender": "Female",
        "age": 64,
        "country": "Tanzania"
    },
    {
        "id": 12,
        "first_name": "Belinda",
        "last_name": "Veschi",
        "email": "bveschib@stumbleupon.com",
        "password": "s6Z16yjV",
        "address": "64 Hollow Ridge Parkway",
        "gender": "Female",
        "age": 85,
        "country": "Nigeria"
    },
    {
        "id": 13,
        "first_name": "Aggy",
        "last_name": "Children",
        "email": "achildrenc@vkontakte.ru",
        "password": "6XdXTvy",
        "address": "3 Kensington Circle",
        "gender": "Female",
        "age": 120,
        "country": "Indonesia"
    },
    {
        "id": 14,
        "first_name": "Reuven",
        "last_name": "Biggen",
        "email": "rbiggend@gov.uk",
        "password": "GTJn2UR",
        "address": "469 Homewood Alley",
        "gender": "Male",
        "age": 2,
        "country": "Malaysia"
    },
    {
        "id": 15,
        "first_name": "Calypso",
        "last_name": "Zanuciolii",
        "email": "czanucioliie@desdev.cn",
        "password": "UH1jsV8QDRp",
        "address": "9 Farragut Hill",
        "gender": "Female",
        "age": 73,
        "country": "Mexico"
    },
    {
        "id": 16,
        "first_name": "Gauthier",
        "last_name": "Eckert",
        "email": "geckertf@pinterest.com",
        "password": "navu8Drx",
        "address": "24523 Russell Junction",
        "gender": "Male",
        "age": 64,
        "country": "Guatemala"
    },
    {
        "id": 17,
        "first_name": "Josephine",
        "last_name": "Castiblanco",
        "email": "jcastiblancog@unesco.org",
        "password": "BxTcvSTO",
        "address": "058 Loeprich Trail",
        "gender": "Female",
        "age": 108,
        "country": "Indonesia"
    },
    {
        "id": 18,
        "first_name": "Randi",
        "last_name": "Burdfield",
        "email": "rburdfieldh@lulu.com",
        "password": "P6GToI",
        "address": "48 Sunbrook Center",
        "gender": "Female",
        "age": 68,
        "country": "Nigeria"
    },
    {
        "id": 19,
        "first_name": "Belvia",
        "last_name": "Waylett",
        "email": "bwayletti@msu.edu",
        "password": "nyS89eB",
        "address": "60609 Cascade Circle",
        "gender": "Female",
        "age": 47,
        "country": "China"
    },
    {
        "id": 20,
        "first_name": "Mela",
        "last_name": "Paolini",
        "email": "mpaolinij@constantcontact.com",
        "password": "4EI9mlr",
        "address": "7 Muir Terrace",
        "gender": "Female",
        "age": 11,
        "country": "China"
    }
]